covasim/README.rst
covasim/__init__.py
covasim/analysis.py
covasim/base.py
covasim/defaults.py
covasim/immunity.py
covasim/interventions.py
covasim/misc.py
covasim/parameters.py
covasim/people.py
covasim/plotting.py
covasim/population.py
covasim/requirements.py
covasim/run.py
covasim/settings.py
covasim/sim.py
covasim/utils.py
covasim/version.py
covasim/data/__init__.py
covasim/data/country_age_data.py
covasim/data/household_size_data.py
covasim/data/loaders.py
covasim/data/state_age_data.py
covasim/data/assets/Mulish-Black.ttf
covasim/data/assets/Mulish-BlackItalic.ttf
covasim/data/assets/Mulish-Bold.ttf
covasim/data/assets/Mulish-BoldItalic.ttf
covasim/data/assets/Mulish-ExtraBold.ttf
covasim/data/assets/Mulish-ExtraBoldItalic.ttf
covasim/data/assets/Mulish-ExtraLight.ttf
covasim/data/assets/Mulish-ExtraLightItalic.ttf
covasim/data/assets/Mulish-Italic-VariableFont_wght.ttf
covasim/data/assets/Mulish-Italic.ttf
covasim/data/assets/Mulish-Light.ttf
covasim/data/assets/Mulish-LightItalic.ttf
covasim/data/assets/Mulish-Medium.ttf
covasim/data/assets/Mulish-MediumItalic.ttf
covasim/data/assets/Mulish-Regular.ttf
covasim/data/assets/Mulish-SemiBold.ttf
covasim/data/assets/Mulish-SemiBoldItalic.ttf
covasim/data/assets/Mulish-VariableFont_wght.ttf
covasim/data/assets/Rosario-Bold.ttf
covasim/data/assets/Rosario-BoldItalic.ttf
covasim/data/assets/Rosario-Italic.ttf
covasim/data/assets/Rosario-Light.ttf
covasim/data/assets/Rosario-LightItalic.ttf
covasim/data/assets/Rosario-Medium.ttf
covasim/data/assets/Rosario-MediumItalic.ttf
covasim/data/assets/Rosario-Regular.ttf
covasim/data/assets/Rosario-SemiBold.ttf
covasim/data/assets/Rosario-SemiBoldItalic.ttf
covasim/data/assets/license-mulish.rst
covasim/data/assets/license-rosario.rst
covasim/regression/README.rst
covasim/regression/pars_v0.30.4.json
covasim/regression/pars_v0.31.0.json
covasim/regression/pars_v0.32.0.json
covasim/regression/pars_v1.0.0.json
covasim/regression/pars_v1.0.1.json
covasim-3.1.6.dist-info/LICENSE
covasim-3.1.6.dist-info/METADATA
covasim-3.1.6.dist-info/WHEEL
covasim-3.1.6.dist-info/top_level.txt
covasim-3.1.6.dist-info/RECORD
