Metadata-Version: 2.1
Name: covasim
Version: 3.1.6
Summary: COVID-19 Agent-based Simulator
Home-page: http://covasim.org
Author: Cliff Kerr, Robyn Stuart, Romesh Abeysuriya, Dina Mistry, Lauren George, and Daniel Klein, on behalf of the IDM COVID-19 Response Team
Author-email: info@covasim.org
Keywords: COVID,COVID-19,coronavirus,SARS-CoV-2,stochastic,agent-based model,interventions,epidemiology
Platform: OS Independent
Classifier: Environment :: Console
Classifier: Intended Audience :: Science/Research
Classifier: License :: Other/Proprietary License
Classifier: Operating System :: OS Independent
Classifier: Programming Language :: Python
Classifier: Topic :: Software Development :: Libraries :: Python Modules
Classifier: Development Status :: 5 - Production/Stable
Classifier: Programming Language :: Python :: 3.7
Classifier: Programming Language :: Python :: 3.8
License-File: LICENSE
Requires-Dist: numpy
Requires-Dist: numba
Requires-Dist: pandas
Requires-Dist: scipy
Requires-Dist: statsmodels
Requires-Dist: matplotlib
Requires-Dist: sciris (>=2.0.4)
Provides-Extra: full
Requires-Dist: plotly ; extra == 'full'
Requires-Dist: fire ; extra == 'full'
Requires-Dist: optuna ; extra == 'full'
Requires-Dist: synthpops ; extra == 'full'
Requires-Dist: parestlib ; extra == 'full'
